userspy/__init__.py
userspy/sqlite.py
userspy/users.py
userspy-0.0.4.dist-info/LICENSE
userspy-0.0.4.dist-info/METADATA
userspy-0.0.4.dist-info/WHEEL
userspy-0.0.4.dist-info/top_level.txt
userspy-0.0.4.dist-info/RECORD
