Metadata-Version: 2.1
Name: userspy
Version: 0.0.4
Summary: An easy app for managing users.
Home-page: https://github.com/Okirshen/userspy
Author: Ofri Kirshen
Author-email: okirshen@gmail.com
License: UNKNOWN
Platform: UNKNOWN
Classifier: Programming Language :: Python :: 3
Classifier: License :: OSI Approved :: MIT License
Classifier: Operating System :: OS Independent
